lab2.srcs/sources_1/new/light_controller.sv
`timescale 1ns / 1ps
//////////////////////////////////////////////////////////////////////////////////
// Company: 
// Engineer: 
// 
// Create Date: 09/26/2025 02:41:39 PM
// Design Name: 
// Module Name: light_controller
// Project Name: 
// Target Devices: 
// Tool Versions: 
// Description: 
// 
// Dependencies: 
// 
// Revision:
// Revision 0.01 - File Created
// Additional Comments:
// 
//////////////////////////////////////////////////////////////////////////////////


module light_controller #(parameter N) (
    input wire clk,
    input wire rst,
    input wire button,
    output wire [2:0] light_state
    );
    
   reg [2:0] light_state_reg;
   reg button_prev;
   reg [31:0] counter;
   
    assign light_state = light_state_reg;
    
   always @ (posedge clk) begin
        if (rst) begin 
            button_prev <= 1'b0;
            light_state_reg <= 3'b0;
            counter <= 0;
        end else begin
            if (!button) begin
                light_state_reg <= 3'b0;
                counter <= 0;
            end else if (button > button_prev) begin
                light_state_reg <= 1;
                counter <= 0;
            end 
            
            else if (button == button_prev) begin
                if (counter == N - 1) begin 
                    counter <= 0;
                    if (light_state_reg == 3'b111)  
                        light_state_reg <= 3'b001; // wrap to 1
                    else 
                        light_state_reg <= light_state_reg + 3'b001;
              end else begin
                counter <= counter + 1;
              end 
           end 
           
           button_prev <= button;
       end
            
   end
        
endmodule

lab2.srcs/sim_1/new/light_controller_tb.sv
`timescale 1ns/1ps

module tb_light_controller;

    reg clk;
    reg rst;
    reg button;

    wire [2:0] light_state_N1;
    wire [2:0] light_state_N10;
    wire [2:0] light_state_N100ns;

    light_controller #(1) dut_N1 (
        .clk(clk),
        .rst(rst),
        .button(button),
        .light_state(light_state_N1)
    );

    light_controller #(10) dut_N10 (
        .clk(clk),
        .rst(rst),
        .button(button),
        .light_state(light_state_N10)
    );

    light_controller #(10) dut_N100ns (
        .clk(clk),
        .rst(rst),
        .button(button),
        .light_state(light_state_N100ns)
    );

    always #5ns clk = ~clk;

    initial begin
        clk    = 0;
        rst    = 1;
        button = 0;

        repeat (2) @(posedge clk); rst = 0;

        button = 1;
        repeat(50) @(posedge clk);
        button = 0;

        repeat(10) @(posedge clk);
    end

endmodule

lab2.sim/sim_1/behav/xsim/light_controller_tb.vcd
$date
   Thu Oct  2 20:43:02 2025
$end

$version
  2025.1.0
  $dumpfile ("light_controller_tb.vcd") 
$end

$timescale
  1ps
$end

$scope module tb_light_controller $end
$var reg 1 ! clk $end
$var reg 1 " rst $end
$var reg 1 # button $end
$var wire 3 $ light_state_N1 [2:0] $end
$var wire 3 % light_state_N10 [2:0] $end
$var wire 3 & light_state_N100ns [2:0] $end
$scope module dut_N1 $end
$var wire 1 ' clk $end
$var wire 1 ( rst $end
$var wire 1 ) button $end
$var wire 3 $ light_state [2:0] $end
$var reg 3 * light_state_reg [2:0] $end
$var reg 1 + button_prev $end
$var reg 32 , counter [31:0] $end
$upscope $end
$scope module dut_N10 $end
$var wire 1 - clk $end
$var wire 1 . rst $end
$var wire 1 / button $end
$var wire 3 % light_state [2:0] $end
$var reg 3 0 light_state_reg [2:0] $end
$var reg 1 1 button_prev $end
$var reg 32 2 counter [31:0] $end
$upscope $end
$scope module dut_N100ns $end
$var wire 1 3 clk $end
$var wire 1 4 rst $end
$var wire 1 5 button $end
$var wire 3 & light_state [2:0] $end
$var reg 3 6 light_state_reg [2:0] $end
$var reg 1 7 button_prev $end
$var reg 32 8 counter [31:0] $end
$upscope $end
$upscope $end
$enddefinitions $end

#0
$dumpvars
0!
1"
0#
bx $
bx %
bx &
0'
1(
0)
bx *
x+
bx ,
0-
1.
0/
bx 0
x1
bx 2
03
14
05
bx 6
x7
bx 8
$end

#5000
1!
b0 $
b0 %
b0 &
1'
b0 *
0+
b0 ,
1-
b0 0
01
b0 2
13
b0 6
07
b0 8

#10000
0!
0'
0-
03

#15000
1!
1'
1-
13

#20000
0!
0"
1#
0'
0(
1)
0-
0.
1/
03
04
15

#25000
1!
b1 $
b1 %
b1 &
1'
b1 *
1+
1-
b1 0
11
13
b1 6
17

#30000
0!
0'
0-
03

#35000
1!
b10 $
1'
b10 *
1-
b1 2
13
b1 8

#40000
0!
0'
0-
03

#45000
1!
b11 $
1'
b11 *
1-
b10 2
13
b10 8

#50000
0!
0'
0-
03

#55000
1!
b100 $
1'
b100 *
1-
b11 2
13
b11 8

#60000
0!
0'
0-
03

#65000
1!
b101 $
1'
b101 *
1-
b100 2
13
b100 8

#70000
0!
0'
0-
03

#75000
1!
b110 $
1'
b110 *
1-
b101 2
13
b101 8

#80000
0!
0'
0-
03

#85000
1!
b111 $
1'
b111 *
1-
b110 2
13
b110 8

#90000
0!
0'
0-
03

#95000
1!
b1 $
1'
b1 *
1-
b111 2
13
b111 8

#100000
0!
0'
0-
03

#105000
1!
b10 $
1'
b10 *
1-
b1000 2
13
b1000 8

#110000
0!
0'
0-
03

#115000
1!
b11 $
1'
b11 *
1-
b1001 2
13
b1001 8

#120000
0!
0'
0-
03

#125000
1!
b100 $
b10 %
b10 &
1'
b100 *
1-
b10 0
b0 2
13
b10 6
b0 8

#130000
0!
0'
0-
03

#135000
1!
b101 $
1'
b101 *
1-
b1 2
13
b1 8

#140000
0!
0'
0-
03

#145000
1!
b110 $
1'
b110 *
1-
b10 2
13
b10 8

#150000
0!
0'
0-
03

#155000
1!
b111 $
1'
b111 *
1-
b11 2
13
b11 8

#160000
0!
0'
0-
03

#165000
1!
b1 $
1'
b1 *
1-
b100 2
13
b100 8

#170000
0!
0'
0-
03

#175000
1!
b10 $
1'
b10 *
1-
b101 2
13
b101 8

#180000
0!
0'
0-
03

#185000
1!
b11 $
1'
b11 *
1-
b110 2
13
b110 8

#190000
0!
0'
0-
03

#195000
1!
b100 $
1'
b100 *
1-
b111 2
13
b111 8

#200000
0!
0'
0-
03

#205000
1!
b101 $
1'
b101 *
1-
b1000 2
13
b1000 8

#210000
0!
0'
0-
03

#215000
1!
b110 $
1'
b110 *
1-
b1001 2
13
b1001 8

#220000
0!
0'
0-
03

#225000
1!
b111 $
b11 %
b11 &
1'
b111 *
1-
b11 0
b0 2
13
b11 6
b0 8

#230000
0!
0'
0-
03

#235000
1!
b1 $
1'
b1 *
1-
b1 2
13
b1 8

#240000
0!
0'
0-
03

#245000
1!
b10 $
1'
b10 *
1-
b10 2
13
b10 8

#250000
0!
0'
0-
03

#255000
1!
b11 $
1'
b11 *
1-
b11 2
13
b11 8

#260000
0!
0'
0-
03

#265000
1!
b100 $
1'
b100 *
1-
b100 2
13
b100 8

#270000
0!
0'
0-
03

#275000
1!
b101 $
1'
b101 *
1-
b101 2
13
b101 8

#280000
0!
0'
0-
03

#285000
1!
b110 $
1'
b110 *
1-
b110 2
13
b110 8

#290000
0!
0'
0-
03

#295000
1!
b111 $
1'
b111 *
1-
b111 2
13
b111 8

#300000
0!
0'
0-
03

#305000
1!
b1 $
1'
b1 *
1-
b1000 2
13
b1000 8

#310000
0!
0'
0-
03

#315000
1!
b10 $
1'
b10 *
1-
b1001 2
13
b1001 8

#320000
0!
0'
0-
03

#325000
1!
b11 $
b100 %
b100 &
1'
b11 *
1-
b100 0
b0 2
13
b100 6
b0 8

#330000
0!
0'
0-
03

#335000
1!
b100 $
1'
b100 *
1-
b1 2
13
b1 8

#340000
0!
0'
0-
03

#345000
1!
b101 $
1'
b101 *
1-
b10 2
13
b10 8

#350000
0!
0'
0-
03

#355000
1!
b110 $
1'
b110 *
1-
b11 2
13
b11 8

#360000
0!
0'
0-
03

#365000
1!
b111 $
1'
b111 *
1-
b100 2
13
b100 8

#370000
0!
0'
0-
03

#375000
1!
b1 $
1'
b1 *
1-
b101 2
13
b101 8

#380000
0!
0'
0-
03

#385000
1!
b10 $
1'
b10 *
1-
b110 2
13
b110 8

#390000
0!
0'
0-
03

#395000
1!
b11 $
1'
b11 *
1-
b111 2
13
b111 8

#400000
0!
0'
0-
03

#405000
1!
b100 $
1'
b100 *
1-
b1000 2
13
b1000 8

#410000
0!
0'
0-
03

#415000
1!
b101 $
1'
b101 *
1-
b1001 2
13
b1001 8

#420000
0!
0'
0-
03

#425000
1!
b110 $
b101 %
b101 &
1'
b110 *
1-
b101 0
b0 2
13
b101 6
b0 8

#430000
0!
0'
0-
03

#435000
1!
b111 $
1'
b111 *
1-
b1 2
13
b1 8

#440000
0!
0'
0-
03

#445000
1!
b1 $
1'
b1 *
1-
b10 2
13
b10 8

#450000
0!
0'
0-
03

#455000
1!
b10 $
1'
b10 *
1-
b11 2
13
b11 8

#460000
0!
0'
0-
03

#465000
1!
b11 $
1'
b11 *
1-
b100 2
13
b100 8

#470000
0!
0'
0-
03

#475000
1!
b100 $
1'
b100 *
1-
b101 2
13
b101 8

#480000
0!
0'
0-
03

#485000
1!
b101 $
1'
b101 *
1-
b110 2
13
b110 8

#490000
0!
0'
0-
03

#495000
1!
b110 $
1'
b110 *
1-
b111 2
13
b111 8

#500000
0!
0'
0-
03

#505000
1!
b111 $
1'
b111 *
1-
b1000 2
13
b1000 8

#510000
0!
0'
0-
03

#515000
1!
0#
b0 $
b0 %
b0 &
1'
0)
b0 *
0+
1-
0/
b0 0
01
b0 2
13
05
b0 6
07
b0 8

